README.rst
requests_foauth.py
setup.py
requests_foauth.egg-info/PKG-INFO
requests_foauth.egg-info/SOURCES.txt
requests_foauth.egg-info/dependency_links.txt
requests_foauth.egg-info/not-zip-safe
requests_foauth.egg-info/top_level.txt